utility/__init__.py
utility/datetimes.py
utility/db.py
utility/decorator.py
utility/file_dir.py
utility/formater.py
utility/gateway_connector.py
utility/logger.py
utility/maths.py
utility/network.py
utility/pkl.py
utility/process.py
utility/proxy.py
utility/requesting.py
utility/service.py
utility/ssh.py
utility/structures.py
starco_utility-1.3.4.dist-info/METADATA
starco_utility-1.3.4.dist-info/WHEEL
starco_utility-1.3.4.dist-info/top_level.txt
starco_utility-1.3.4.dist-info/RECORD
