Metadata-Version: 2.1
Name: starco-utility
Version: 1.3.4
Summary: Starco utility package
Author-email: Mojtaba Tahmasbi <m.tahmasbi0111@yahoo.com>
Requires-Python: >=3.6
Requires-Dist: cryptography
Requires-Dist: psutil
Requires-Dist: requests[socks]
Requires-Dist: urllib3
Requires-Dist: PySocks
Requires-Dist: python-socks
Requires-Dist: easy-db==0.9.15
Requires-Dist: jdatetime
Requires-Dist: deep-translator
Requires-Dist: colorama
Requires-Dist: aiohttp
Requires-Dist: paramiko
